disperseNN2/__init__.py
disperseNN2/check_params.py
disperseNN2/data_generation.py
disperseNN2/disperseNN2.py
disperseNN2/process_input.py
disperseNN2/read_input.py
dispersenn2-0.0.6.dist-info/METADATA
dispersenn2-0.0.6.dist-info/WHEEL
dispersenn2-0.0.6.dist-info/entry_points.txt
dispersenn2-0.0.6.dist-info/RECORD
